pythonagent/1.py
pythonagent/__init__.py
pythonagent/config.py
pythonagent/find.py
pythonagent/find_mod_cls_name.py
pythonagent/lang.py
pythonagent/lib.py
pythonagent/main.py
pythonagent/run.py
pythonagent/sqins.py
pythonagent/test.py
pythonagent/test_udp.py
pythonagent/agent/__init__.py
pythonagent/agent/initjsonoldaftertxt.py
pythonagent/agent/oldinit.py
pythonagent/agent/internal/2agent.py
pythonagent/agent/internal/3agent.py
pythonagent/agent/internal/__init__.py
pythonagent/agent/internal/agent.py
pythonagent/agent/internal/framesinfo.py
pythonagent/agent/internal/intercept_module.py
pythonagent/agent/internal/logs.py
pythonagent/agent/internal/profile.py
pythonagent/agent/internal/proxy_old.py
pythonagent/agent/internal/udp.py
pythonagent/agent/internal/udp_message.py
pythonagent/agent/probes/__init__.py
pythonagent/agent/probes/base.py
pythonagent/agent/probes/Instrumentation/__init__.py
pythonagent/agent/probes/Instrumentation/find.py
pythonagent/agent/probes/Instrumentation/parser.py
pythonagent/agent/probes/Instrumentation/parserjson.py
pythonagent/agent/probes/Instrumentation/parsertxt.py
pythonagent/agent/probes/cache/__init__.py
pythonagent/agent/probes/cache/redis.py
pythonagent/agent/probes/dynamodb/__init__.py
pythonagent/agent/probes/dynamodb/dynamo.py
pythonagent/agent/probes/elasticdb/__init__.py
pythonagent/agent/probes/elasticdb/aelastic.py
pythonagent/agent/probes/frameworks/__init__.py
pythonagent/agent/probes/frameworks/agentprofiler.py
pythonagent/agent/probes/frameworks/aisess.py
pythonagent/agent/probes/frameworks/bottle.py
pythonagent/agent/probes/frameworks/cherry.py
pythonagent/agent/probes/frameworks/django.py
pythonagent/agent/probes/frameworks/falcon.py
pythonagent/agent/probes/frameworks/flask.py
pythonagent/agent/probes/frameworks/pyramid.py
pythonagent/agent/probes/frameworks/test.py
pythonagent/agent/probes/frameworks/tornado_web.py
pythonagent/agent/probes/frameworks/wsgi.py
pythonagent/agent/probes/havoc/__init__.py
pythonagent-0.0.1.dist-info/LICENSE
pythonagent-0.0.1.dist-info/METADATA
pythonagent-0.0.1.dist-info/WHEEL
pythonagent-0.0.1.dist-info/top_level.txt
pythonagent-0.0.1.dist-info/RECORD
